pyfnip/__init__.py
pyfnip-0.2.dist-info/METADATA
pyfnip-0.2.dist-info/RECORD
pyfnip-0.2.dist-info/WHEEL
pyfnip-0.2.dist-info/top_level.txt
